LICENSE.md
README.md
pyproject.toml
setup.cfg
setup.py
ass_parser/__init__.py
ass_parser/ass_color.py
ass_parser/ass_event.py
ass_parser/ass_file.py
ass_parser/ass_style.py
ass_parser/errors.py
ass_parser/observable.py
ass_parser/observable_mapping_mixin.py
ass_parser/observable_object_mixin.py
ass_parser/observable_sequence_mixin.py
ass_parser/py.typed
ass_parser/reader.py
ass_parser/util.py
ass_parser/writer.py
ass_parser.egg-info/PKG-INFO
ass_parser.egg-info/SOURCES.txt
ass_parser.egg-info/dependency_links.txt
ass_parser.egg-info/requires.txt
ass_parser.egg-info/top_level.txt
ass_parser/ass_sections/__init__.py
ass_parser/ass_sections/ass_base_section.py
ass_parser/ass_sections/ass_base_tabular_section.py
ass_parser/ass_sections/ass_event_list.py
ass_parser/ass_sections/ass_key_value_mapping.py
ass_parser/ass_sections/ass_script_info.py
ass_parser/ass_sections/ass_string_table.py
ass_parser/ass_sections/ass_style_list.py
ass_parser/ass_sections/const.py
ass_parser/tests/__init__.py
ass_parser/tests/conftest.py
ass_parser/tests/test_ass_color.py
ass_parser/tests/test_ass_event.py
ass_parser/tests/test_ass_event_list.py
ass_parser/tests/test_ass_file.py
ass_parser/tests/test_ass_key_value_mapping.py
ass_parser/tests/test_ass_script_info.py
ass_parser/tests/test_ass_string_table.py
ass_parser/tests/test_ass_style.py
ass_parser/tests/test_ass_style_list.py
ass_parser/tests/test_documentation.py
ass_parser/tests/test_observable.py
ass_parser/tests/test_observable_mapping_mixin.py
ass_parser/tests/test_observable_object_mixin.py
ass_parser/tests/test_observable_sequence_mixin.py
ass_parser/tests/test_reader.py
ass_parser/tests/test_writer.py