Metadata-Version: 2.1
Name: ass-parser
Version: 1.0
Summary: "Parse ASS subtitle format."
Home-page: https://github.com/bubblesub/ass_parser
Author: Marcin Kurczewski
Author-email: rr-@sakuya.pl
License: MIT
Platform: UNKNOWN
Classifier: Environment :: Other Environment
Classifier: Development Status :: 5 - Production/Stable
Classifier: Intended Audience :: Developers
Classifier: License :: OSI Approved :: MIT License
Classifier: Natural Language :: English
Classifier: Operating System :: OS Independent
Classifier: Programming Language :: Python :: 3.9
Classifier: Topic :: Text Processing
Classifier: Topic :: Software Development :: Libraries :: Python Modules
Requires-Python: >=3.9
Provides-Extra: test
License-File: LICENSE.md
